torii_sim_wasm-0.2.0.dist-info/METADATA
torii_sim_wasm-0.2.0.dist-info/WHEEL
torii_sim_wasm-0.2.0.dist-info/licenses/LICENSE
torii_sim_wasm-0.2.0.dist-info/licenses/LICENSE.docs
torii_sim_wasm/__init__.py
torii_sim_wasm/_wasm_engine.cpython-314-i386-linux-gnu.so
torii_sim_wasm/_wasm_engine/__init__.pyi
torii_sim_wasm/py.typed
torii_sim_wasm/wasmclock.py
torii_sim_wasm/wasmcoro.py
torii_sim_wasm/wasmrtl.py
torii_sim_wasm-0.2.0.dist-info/RECORD
