Metadata-Version: 2.4
Name: torii-sim-wasm
Version: 0.2.0
Classifier: Development Status :: 4 - Beta
Classifier: Intended Audience :: Developers
Classifier: Intended Audience :: Education
Classifier: Intended Audience :: Information Technology
Classifier: Intended Audience :: Science/Research
Classifier: Operating System :: MacOS :: MacOS X
Classifier: Operating System :: Microsoft :: Windows
Classifier: Operating System :: POSIX :: Linux
Classifier: Programming Language :: Python :: 3.11
Classifier: Programming Language :: Python :: 3.12
Classifier: Programming Language :: Python :: 3.13
Classifier: Programming Language :: Python :: 3.14
Classifier: Programming Language :: Python :: Implementation :: CPython
Classifier: Programming Language :: Python :: Implementation :: PyPy
Classifier: Topic :: Scientific/Engineering
Classifier: Topic :: Scientific/Engineering :: Electronic Design Automation (EDA)
Classifier: Topic :: Software Development
Classifier: Topic :: Software Development :: Embedded Systems
Classifier: Topic :: Software Development :: Libraries
Classifier: Typing :: Typed
Requires-Dist: torii>=0.8.0,<1.0
Requires-Dist: pyvcd
Requires-Dist: nox ; extra == 'dev'
Provides-Extra: dev
License-File: LICENSE
License-File: LICENSE.docs
Summary: A WASM based simulation backend for Torii
Keywords: Torii,Simulation,WASM
Author: Torii Contributors
Author-email: Aki Van Ness <aki@lethalbit.net>, Miika Alikirri <duck@duckie.fi>
License-Expression: BSD-2-Clause
Requires-Python: >=3.11
Project-URL: source, https://github.com/shrine-maiden-heavy-industries/torii-sim-wasm
Project-URL: issues, https://github.com/shrine-maiden-heavy-industries/torii-sim-wasm/issues
Project-URL: documentation, https://torii.shmdn.link/latest
